pylimer_tools_cpp.cpython-39-darwin.so
pylimer_tools/__init__.py
pylimer_tools/analyse_networks.py
pylimer_tools/basic_lammps_structure_stats.py
pylimer_tools/displace_randomly.py
pylimer_tools/generate_network.py
pylimer_tools/calc/__init__.py
pylimer_tools/calc/mehp_utilities.py
pylimer_tools/calc/miller_macosko_theory.py
pylimer_tools/calc/stoichiometric_relationships.py
pylimer_tools/calc/structure_analysis.py
pylimer_tools/data/everaers_et_al_unit_properties.json
pylimer_tools/data/everaers_et_al_unit_properties.xlsx
pylimer_tools/io/__init__.py
pylimer_tools/io/bead_spring_parameter_provider.py
pylimer_tools/io/extract_thermo_data.py
pylimer_tools/io/polymer_data.py
pylimer_tools/io/read_lammps_output_file.py
pylimer_tools/io/read_pylimer_tools_output_file.py
pylimer_tools/io/unit_styles.py
pylimer_tools/utils/__init__.py
pylimer_tools/utils/cache_utility.py
pylimer_tools/utils/data_utility.py
pylimer_tools/utils/optimize_dataframe.py
pylimer_tools-0.3.13.dist-info/licenses/LICENSE
pylimer_tools_cpp/CMakeLists.txt
pylimer_tools_cpp/pylimer_tools.cpp
pylimer_tools_cpp/version_config.h.in
pylimer_tools_cpp/calc/Correlator.cpp
pylimer_tools_cpp/calc/Correlator.h
pylimer_tools_cpp/calc/MMTanalysis.h
pylimer_tools_cpp/calc/NormalModeAnalyzer.cpp
pylimer_tools_cpp/calc/NormalModeAnalyzer.h
pylimer_tools_cpp/entities/Atom.h
pylimer_tools_cpp/entities/AtomGraphParent.cpp
pylimer_tools_cpp/entities/AtomGraphParent.h
pylimer_tools_cpp/entities/Box.h
pylimer_tools_cpp/entities/EigenNeighbourList.cpp
pylimer_tools_cpp/entities/EigenNeighbourList.h
pylimer_tools_cpp/entities/Molecule.cpp
pylimer_tools_cpp/entities/Molecule.h
pylimer_tools_cpp/entities/NeighbourList.cpp
pylimer_tools_cpp/entities/NeighbourList.h
pylimer_tools_cpp/entities/Universe.cpp
pylimer_tools_cpp/entities/Universe.h
pylimer_tools_cpp/entities/UniverseSequence.cpp
pylimer_tools_cpp/entities/UniverseSequence.h
pylimer_tools_cpp/io/AveFileReader.cpp
pylimer_tools_cpp/io/AveFileReader.h
pylimer_tools_cpp/io/CSVSplitter.h
pylimer_tools-0.3.13.dist-info/METADATA
pylimer_tools-0.3.13.dist-info/WHEEL
pylimer_tools-0.3.13.dist-info/entry_points.txt
pylimer_tools-0.3.13.dist-info/top_level.txt
pylimer_tools-0.3.13.dist-info/RECORD
