Metadata-Version: 2.4
Name: pylimer_tools
Version: 0.3.13
Summary: A toolkit for handling bead-spring polymers and LAMMPS output in Python
Home-page: https://github.com/GenieTim/pylimer-tools
Author: Tim Bernhard
Author-email: tim@bernhard.dev
License: GPL-3.0-or-later
Keywords: Polymer,Chemistry,Network,LAMMPS,Science
Classifier: Programming Language :: Python :: 3
Classifier: Programming Language :: Python :: 3.9
Classifier: Programming Language :: Python :: 3.10
Classifier: Programming Language :: Python :: 3.11
Classifier: Programming Language :: Python :: 3.12
Classifier: Programming Language :: Python :: 3.13
Classifier: Operating System :: OS Independent
Requires-Python: >=3.9
License-File: LICENSE
Provides-Extra: test
Requires-Dist: unittest; extra == "test"
Dynamic: author
Dynamic: author-email
Dynamic: classifier
Dynamic: description
Dynamic: description-content-type
Dynamic: home-page
Dynamic: keywords
Dynamic: license
Dynamic: license-file
Dynamic: provides-extra
Dynamic: requires-python
Dynamic: summary
